checklinks/__init__.py
checklinks/__version__.py
checklinks/check_links.py
checklinks/url.py
checklinks-0.4.16918818.dist-info/DESCRIPTION.rst
checklinks-0.4.16918818.dist-info/METADATA
checklinks-0.4.16918818.dist-info/RECORD
checklinks-0.4.16918818.dist-info/WHEEL
checklinks-0.4.16918818.dist-info/metadata.json
checklinks-0.4.16918818.dist-info/top_level.txt
