Metadata-Version: 2.0
Name: checklinks
Version: 0.4.16918818
Summary: Fetch, find and report broken links on all pages of a website.
Home-page: https://gitlab.com/alexbenfica/check-links/
Author: Alex Benfica
Author-email: alexbenfica@gmail.com
License: Apache 2.0
Keywords: broken links check checker invalid urls url
Platform: UNKNOWN
Requires-Dist: requests
Requires-Dist: markdown
Requires-Dist: bs4
Requires-Dist: colorama
